wemeet_openapi/__init__.py
wemeet_openapi/client.py
wemeet_openapi/core/__init__.py
wemeet_openapi/core/authenticator.py
wemeet_openapi/core/config.py
wemeet_openapi/core/constants.py
wemeet_openapi/core/exception.py
wemeet_openapi/core/serializer.py
wemeet_openapi/core/utils.py
wemeet_openapi/core/version.py
wemeet_openapi/core/xhttp/__init__.py
wemeet_openapi/core/xhttp/authenticator.py
wemeet_openapi/core/xhttp/client.py
wemeet_openapi/core/xhttp/client_test.py
wemeet_openapi/core/xhttp/request.py
wemeet_openapi/core/xhttp/response.py
wemeet_openapi/core/xhttp/serializer.py
wemeet_openapi/service/__init__.py
wemeet_openapi/service/meetings/__init__.py
wemeet_openapi/service/meetings/api/__init__.py
wemeet_openapi/service/meetings/api/meetings_api.py
wemeet_openapi/service/meetings/model/__init__.py
wemeet_openapi/service/meetings/model/v1_meeting_set_waiting_room_welcome_message_post200_response.py
wemeet_openapi/service/meetings/model/v1_meeting_set_waiting_room_welcome_message_post_request.py
wemeet_openapi/service/meetings/model/v1_meetings_get200_response.py
wemeet_openapi/service/meetings/model/v1_meetings_get200_response_meeting_info_list_inner.py
wemeet_openapi/service/meetings/model/v1_meetings_get200_response_meeting_info_list_inner_current_co_hosts_inner.py
wemeet_openapi/service/meetings/model/v1_meetings_get200_response_meeting_info_list_inner_current_hosts_inner.py
wemeet_openapi/service/meetings/model/v1_meetings_get200_response_meeting_info_list_inner_guests_inner.py
wemeet_openapi/service/meetings/model/v1_meetings_get200_response_meeting_info_list_inner_live_config.py
wemeet_openapi/service/meetings/model/v1_meetings_get200_response_meeting_info_list_inner_live_config_live_watermark.py
wemeet_openapi/service/meetings/model/v1_meetings_get200_response_meeting_info_list_inner_recurring_rule.py
wemeet_openapi/service/meetings/model/v1_meetings_get200_response_meeting_info_list_inner_settings.py
wemeet_openapi-1.0.0.18.dist-info/METADATA
wemeet_openapi-1.0.0.18.dist-info/WHEEL
wemeet_openapi-1.0.0.18.dist-info/top_level.txt
wemeet_openapi-1.0.0.18.dist-info/RECORD
