Metadata-Version: 2.1
Name: wemeet-openapi
Version: 1.0.0.18
Summary: OpenAPI SDK for Python
Home-page: https://git.code.tencent.com/open_sdk/python
Author: Leosluo
Author-email: leosluo@tencent.com
License: UNKNOWN
Project-URL: Source, https://git.code.tencent.com/open_sdk/python
Keywords: Wemeet,OpenAPI SDK
Platform: UNKNOWN
Requires-Python: >=3.7
Requires-Dist: requests
